CHANGELOG.rst
LICENSE
MANIFEST.in
README.rst
requirements.txt
setup.cfg
setup.py
tests/__init__.py
tests/test_configuration.py
tests/models/__init__.py
tests/models/test_partner.py
tests/models/test_site.py
tests/models/test_siteimport.py
tests/models/test_subscription.py
tests/models/test_user.py
tests/test_integration/__init__.py
tests/test_integration/helpers.py
tests/test_integration/test_case.py
tests/test_integration/test_cname_zone_resource.py
tests/test_integration/test_partner_resource.py
tests/test_integration/test_site_resource.py
tests/test_integration/test_siteimport_resource.py
tests/test_integration/test_subscription_resource.py
tests/test_integration/test_user_resource.py
yolapy/__init__.py
yolapy/configuration.py
yolapy/constants.py
yolapy/services.py
yolapy.egg-info/PKG-INFO
yolapy.egg-info/SOURCES.txt
yolapy.egg-info/dependency_links.txt
yolapy.egg-info/requires.txt
yolapy.egg-info/top_level.txt
yolapy/models/__init__.py
yolapy/models/partner.py
yolapy/models/site.py
yolapy/models/siteimport.py
yolapy/models/subscription.py
yolapy/models/user.py
yolapy/resources/__init__.py
yolapy/resources/campaign.py
yolapy/resources/cname_zone.py
yolapy/resources/partner.py
yolapy/resources/site.py
yolapy/resources/siteimport.py
yolapy/resources/subscription.py
yolapy/resources/user.py
yolapy/resources/wl_task.py