Metadata-Version: 1.1
Name: yolapy
Version: 0.7.0
Summary: Python client for the Yola API
Home-page: https://github.com/yola/yolapy
Author: Yola
Author-email: engineers@yola.com
License: MIT (Expat)
Platform: UNKNOWN
Classifier: License :: OSI Approved :: MIT License
Classifier: Programming Language :: Python :: 2
Classifier: Programming Language :: Python :: 3
Classifier: Topic :: Internet :: WWW/HTTP
